{"toptags":{"tag":[{"count":100,"name":"seen live","url":"https://www.last.fm/tag/seen+live"},{"count":89,"name":"rap","url":"https://www.last.fm/tag/rap"},{"count":83,"name":"Deutschrap","url":"https://www.last.fm/tag/Deutschrap"},{"count":69,"name":"hip hop","url":"https://www.last.fm/tag/hip+hop"},{"count":62,"name":"german","url":"https://www.last.fm/tag/german"},{"count":58,"name":"Hip-Hop","url":"https://www.last.fm/tag/Hip-Hop"},{"count":13,"name":"german hiphop","url":"https://www.last.fm/tag/german+hiphop"},{"count":8,"name":"deutsch","url":"https://www.last.fm/tag/deutsch"},{"count":7,"name":"german rap","url":"https://www.last.fm/tag/german+rap"},{"count":7,"name":"casper","url":"https://www.last.fm/tag/casper"},{"count":6,"name":"bielefeld","url":"https://www.last.fm/tag/bielefeld"},{"count":5,"name":"indie","url":"https://www.last.fm/tag/indie"},{"count":5,"name":"Deutsch Rap","url":"https://www.last.fm/tag/Deutsch+Rap"},{"count":5,"name":"hiphop","url":"https://www.last.fm/tag/hiphop"},{"count":5,"name":"emorap","url":"https://www.last.fm/tag/emorap"},{"count":5,"name":"pop","url":"https://www.last.fm/tag/pop"},{"count":5,"name":"emo","url":"https://www.last.fm/tag/emo"},{"count":5,"name":"post-rock","url":"https://www.last.fm/tag/post-rock"},{"count":4,"name":"German hip hop","url":"https://www.last.fm/tag/German+hip+hop"},{"count":4,"name":"alternative","url":"https://www.last.fm/tag/alternative"},{"count":4,"name":"melancholic","url":"https://www.last.fm/tag/melancholic"},{"count":4,"name":"selfmade records","url":"https://www.last.fm/tag/selfmade+records"},{"count":3,"name":"live gesehen","url":"https://www.last.fm/tag/live+gesehen"},{"count":3,"name":"post-hop","url":"https://www.last.fm/tag/post-hop"},{"count":3,"name":"experimental","url":"https://www.last.fm/tag/experimental"},{"count":3,"name":"emo-rap","url":"https://www.last.fm/tag/emo-rap"},{"count":2,"name":"germany","url":"https://www.last.fm/tag/germany"},{"count":2,"name":"deep","url":"https://www.last.fm/tag/deep"},{"count":2,"name":"live","url":"https://www.last.fm/tag/live"},{"count":2,"name":"Deutsch Hiphop","url":"https://www.last.fm/tag/Deutsch+Hiphop"},{"count":2,"name":"emo rap","url":"https://www.last.fm/tag/emo+rap"},{"count":2,"name":"Caspoooooooooar","url":"https://www.last.fm/tag/Caspoooooooooar"},{"count":2,"name":"niveaurap","url":"https://www.last.fm/tag/niveaurap"},{"count":2,"name":"electronic","url":"https://www.last.fm/tag/electronic"},{"count":2,"name":"soul","url":"https://www.last.fm/tag/soul"},{"count":2,"name":"punk","url":"https://www.last.fm/tag/punk"},{"count":2,"name":"dubstep","url":"https://www.last.fm/tag/dubstep"},{"count":2,"name":"poetic","url":"https://www.last.fm/tag/poetic"},{"count":2,"name":"crossover","url":"https://www.last.fm/tag/crossover"},{"count":2,"name":"german hip-hop","url":"https://www.last.fm/tag/german+hip-hop"},{"count":2,"name":"Southside 2012","url":"https://www.last.fm/tag/Southside+2012"},{"count":1,"name":"metal","url":"https://www.last.fm/tag/metal"},{"count":1,"name":"rock","url":"https://www.last.fm/tag/rock"},{"count":1,"name":"hardcore","url":"https://www.last.fm/tag/hardcore"},{"count":1,"name":"sexy","url":"https://www.last.fm/tag/sexy"},{"count":1,"name":"singer-songwriter","url":"https://www.last.fm/tag/singer-songwriter"},{"count":1,"name":"dance","url":"https://www.last.fm/tag/dance"},{"count":1,"name":"favorites","url":"https://www.last.fm/tag/favorites"},{"count":1,"name":"Deutschrock","url":"https://www.last.fm/tag/Deutschrock"},{"count":1,"name":"dnb","url":"https://www.last.fm/tag/dnb"},{"count":1,"name":"male vocalists","url":"https://www.last.fm/tag/male+vocalists"},{"count":1,"name":"underground","url":"https://www.last.fm/tag/underground"},{"count":1,"name":"alternative rap","url":"https://www.last.fm/tag/alternative+rap"},{"count":1,"name":"Deutscher Hip Hop","url":"https://www.last.fm/tag/Deutscher+Hip+Hop"},{"count":1,"name":"indie rap","url":"https://www.last.fm/tag/indie+rap"},{"count":1,"name":"seen-live","url":"https://www.last.fm/tag/seen-live"},{"count":1,"name":"post rap","url":"https://www.last.fm/tag/post+rap"},{"count":1,"name":"bielefeld 667","url":"https://www.last.fm/tag/bielefeld+667"},{"count":1,"name":"Akord","url":"https://www.last.fm/tag/Akord"},{"count":1,"name":"indie-rap","url":"https://www.last.fm/tag/indie-rap"},{"count":1,"name":"emotional rap","url":"https://www.last.fm/tag/emotional+rap"},{"count":1,"name":"emotional lyrics","url":"https://www.last.fm/tag/emotional+lyrics"},{"count":1,"name":"dickaltaahfett","url":"https://www.last.fm/tag/dickaltaahfett"},{"count":1,"name":"hurricane 2012","url":"https://www.last.fm/tag/hurricane+2012"},{"count":1,"name":"dockville 2011","url":"https://www.last.fm/tag/dockville+2011"},{"count":1,"name":"post hop","url":"https://www.last.fm/tag/post+hop"},{"count":1,"name":"667","url":"https://www.last.fm/tag/667"},{"count":1,"name":"Mitsnakker","url":"https://www.last.fm/tag/Mitsnakker"},{"count":1,"name":"Micha Maat","url":"https://www.last.fm/tag/Micha+Maat"},{"count":1,"name":"minitimer katzenposter","url":"https://www.last.fm/tag/minitimer+katzenposter"},{"count":1,"name":"Aggroschlager","url":"https://www.last.fm/tag/Aggroschlager"},{"count":1,"name":"les bummms boys","url":"https://www.last.fm/tag/les+bummms+boys"},{"count":1,"name":"Sun of a Gun","url":"https://www.last.fm/tag/Sun+of+a+Gun"}],"@attr":{"artist":"Casper"}}}