{"toptags":{"tag":[{"count":100,"name":"dance","url":"https://www.last.fm/tag/dance"},{"count":96,"name":"House","url":"https://www.last.fm/tag/House"},{"count":64,"name":"90s","url":"https://www.last.fm/tag/90s"},{"count":52,"name":"female vocalists","url":"https://www.last.fm/tag/female+vocalists"},{"count":46,"name":"pop","url":"https://www.last.fm/tag/pop"},{"count":11,"name":"groove","url":"https://www.last.fm/tag/groove"},{"count":10,"name":"american","url":"https://www.last.fm/tag/american"},{"count":9,"name":"vocal house","url":"https://www.last.fm/tag/vocal+house"},{"count":6,"name":"electronic","url":"https://www.last.fm/tag/electronic"},{"count":6,"name":"Philadelphia","url":"https://www.last.fm/tag/Philadelphia"},{"count":5,"name":"seen live","url":"https://www.last.fm/tag/seen+live"},{"count":5,"name":"dance pop","url":"https://www.last.fm/tag/dance+pop"},{"count":4,"name":"trance","url":"https://www.last.fm/tag/trance"},{"count":4,"name":"soul","url":"https://www.last.fm/tag/soul"},{"count":4,"name":"USA","url":"https://www.last.fm/tag/USA"},{"count":4,"name":"funk","url":"https://www.last.fm/tag/funk"},{"count":4,"name":"funky","url":"https://www.last.fm/tag/funky"},{"count":4,"name":"house music","url":"https://www.last.fm/tag/house+music"},{"count":4,"name":"eurodance","url":"https://www.last.fm/tag/eurodance"},{"count":3,"name":"club","url":"https://www.last.fm/tag/club"},{"count":3,"name":"deep house","url":"https://www.last.fm/tag/deep+house"},{"count":3,"name":"female vocalist","url":"https://www.last.fm/tag/female+vocalist"},{"count":3,"name":"Soulful house","url":"https://www.last.fm/tag/Soulful+house"},{"count":3,"name":"female vocal","url":"https://www.last.fm/tag/female+vocal"},{"count":3,"name":"funky house","url":"https://www.last.fm/tag/funky+house"},{"count":3,"name":"Pennsylvania","url":"https://www.last.fm/tag/Pennsylvania"},{"count":3,"name":"mid-late90s","url":"https://www.last.fm/tag/mid-late90s"},{"count":3,"name":"crystal waters","url":"https://www.last.fm/tag/crystal+waters"},{"count":2,"name":"vocal","url":"https://www.last.fm/tag/vocal"},{"count":2,"name":"80s","url":"https://www.last.fm/tag/80s"},{"count":2,"name":"singer-songwriter","url":"https://www.last.fm/tag/singer-songwriter"},{"count":2,"name":"Love","url":"https://www.last.fm/tag/Love"},{"count":2,"name":"dance-pop","url":"https://www.last.fm/tag/dance-pop"},{"count":2,"name":"techno","url":"https://www.last.fm/tag/techno"},{"count":2,"name":"songwriter","url":"https://www.last.fm/tag/songwriter"},{"count":2,"name":"Drum and bass","url":"https://www.last.fm/tag/Drum+and+bass"},{"count":2,"name":"remix","url":"https://www.last.fm/tag/remix"},{"count":2,"name":"diva","url":"https://www.last.fm/tag/diva"},{"count":2,"name":"poetry","url":"https://www.last.fm/tag/poetry"},{"count":2,"name":"r&b","url":"https://www.last.fm/tag/r&b"},{"count":2,"name":"party","url":"https://www.last.fm/tag/party"},{"count":2,"name":"gay","url":"https://www.last.fm/tag/gay"},{"count":2,"name":"Random","url":"https://www.last.fm/tag/Random"},{"count":2,"name":"rnb","url":"https://www.last.fm/tag/rnb"},{"count":2,"name":"California","url":"https://www.last.fm/tag/California"},{"count":2,"name":"relaxing","url":"https://www.last.fm/tag/relaxing"},{"count":2,"name":"fun","url":"https://www.last.fm/tag/fun"},{"count":2,"name":"good","url":"https://www.last.fm/tag/good"},{"count":2,"name":"highschool","url":"https://www.last.fm/tag/highschool"},{"count":2,"name":"90s dance","url":"https://www.last.fm/tag/90s+dance"},{"count":2,"name":"shit","url":"https://www.last.fm/tag/shit"},{"count":2,"name":"freestyle","url":"https://www.last.fm/tag/freestyle"},{"count":2,"name":"libra","url":"https://www.last.fm/tag/libra"},{"count":2,"name":"colobocuro","url":"https://www.last.fm/tag/colobocuro"},{"count":2,"name":"1990s","url":"https://www.last.fm/tag/1990s"},{"count":2,"name":"Europop","url":"https://www.last.fm/tag/Europop"},{"count":2,"name":"Retro-pop","url":"https://www.last.fm/tag/Retro-pop"},{"count":2,"name":"anthem","url":"https://www.last.fm/tag/anthem"},{"count":2,"name":"homeless","url":"https://www.last.fm/tag/homeless"},{"count":2,"name":"aleister crowley","url":"https://www.last.fm/tag/aleister+crowley"},{"count":2,"name":"Myjukebox","url":"https://www.last.fm/tag/Myjukebox"},{"count":2,"name":"House Society","url":"https://www.last.fm/tag/House+Society"},{"count":2,"name":"flash house","url":"https://www.last.fm/tag/flash+house"},{"count":2,"name":"spotify","url":"https://www.last.fm/tag/spotify"},{"count":2,"name":"music of my youth","url":"https://www.last.fm/tag/music+of+my+youth"},{"count":2,"name":"need","url":"https://www.last.fm/tag/need"},{"count":2,"name":"grew up on","url":"https://www.last.fm/tag/grew+up+on"},{"count":2,"name":"top40","url":"https://www.last.fm/tag/top40"},{"count":2,"name":"damned good","url":"https://www.last.fm/tag/damned+good"},{"count":2,"name":"Christopher Lee","url":"https://www.last.fm/tag/Christopher+Lee"},{"count":2,"name":"Garage House","url":"https://www.last.fm/tag/Garage+House"},{"count":2,"name":"rocks my socks","url":"https://www.last.fm/tag/rocks+my+socks"},{"count":2,"name":"90s euro disco","url":"https://www.last.fm/tag/90s+euro+disco"},{"count":2,"name":"afterdark","url":"https://www.last.fm/tag/afterdark"},{"count":2,"name":"Very good House","url":"https://www.last.fm/tag/Very+good+House"},{"count":2,"name":"am I west coast swing or not","url":"https://www.last.fm/tag/am+I+west+coast+swing+or+not"},{"count":2,"name":"old school techno","url":"https://www.last.fm/tag/old+school+techno"},{"count":2,"name":"house classics","url":"https://www.last.fm/tag/house+classics"},{"count":2,"name":"listen while its sunny and you feel like driving","url":"https://www.last.fm/tag/listen+while+its+sunny+and+you+feel+like+driving"},{"count":2,"name":"Aleyster Crowley","url":"https://www.last.fm/tag/Aleyster+Crowley"},{"count":2,"name":"techno - trance - electronica","url":"https://www.last.fm/tag/techno+-+trance+-+electronica"},{"count":2,"name":"real mccoy","url":"https://www.last.fm/tag/real+mccoy"},{"count":2,"name":"Argeu california seixas","url":"https://www.last.fm/tag/Argeu+california+seixas"},{"count":2,"name":"Silvio Passos","url":"https://www.last.fm/tag/Silvio+Passos"},{"count":2,"name":"Wilson Seixas","url":"https://www.last.fm/tag/Wilson+Seixas"},{"count":2,"name":"california seixas","url":"https://www.last.fm/tag/california+seixas"},{"count":2,"name":"The Music I Grew Up With","url":"https://www.last.fm/tag/The+Music+I+Grew+Up+With"},{"count":2,"name":"familia","url":"https://www.last.fm/tag/familia"},{"count":2,"name":"aleister","url":"https://www.last.fm/tag/aleister"},{"count":2,"name":"sahkotaivas","url":"https://www.last.fm/tag/sahkotaivas"},{"count":2,"name":"Raul Seixas","url":"https://www.last.fm/tag/Raul+Seixas"},{"count":2,"name":"90s house","url":"https://www.last.fm/tag/90s+house"},{"count":2,"name":"Soul Diva","url":"https://www.last.fm/tag/Soul+Diva"},{"count":2,"name":"oldschool house","url":"https://www.last.fm/tag/oldschool+house"},{"count":2,"name":"la tee dee la dee dooow","url":"https://www.last.fm/tag/la+tee+dee+la+dee+dooow"},{"count":2,"name":"tsebest","url":"https://www.last.fm/tag/tsebest"},{"count":2,"name":"Demmies Dance Mix","url":"https://www.last.fm/tag/Demmies+Dance+Mix"},{"count":2,"name":"FunkySex","url":"https://www.last.fm/tag/FunkySex"},{"count":2,"name":"Female solo artists","url":"https://www.last.fm/tag/Female+solo+artists"},{"count":2,"name":"Amidio Junior","url":"https://www.last.fm/tag/Amidio+Junior"}],"@attr":{"artist":"Crystal Waters"}}}