{"toptags":{"tag":[{"count":100,"name":"blues","url":"https://www.last.fm/tag/blues"},{"count":89,"name":"jazz","url":"https://www.last.fm/tag/jazz"},{"count":83,"name":"soul","url":"https://www.last.fm/tag/soul"},{"count":61,"name":"female vocalists","url":"https://www.last.fm/tag/female+vocalists"},{"count":44,"name":"rhythm and blues","url":"https://www.last.fm/tag/rhythm+and+blues"},{"count":9,"name":"oldies","url":"https://www.last.fm/tag/oldies"},{"count":7,"name":"rnb","url":"https://www.last.fm/tag/rnb"},{"count":7,"name":"Etta James","url":"https://www.last.fm/tag/Etta+James"},{"count":6,"name":"jazz vocal","url":"https://www.last.fm/tag/jazz+vocal"},{"count":6,"name":"60s","url":"https://www.last.fm/tag/60s"},{"count":5,"name":"vocal jazz","url":"https://www.last.fm/tag/vocal+jazz"},{"count":5,"name":"female vocalist","url":"https://www.last.fm/tag/female+vocalist"},{"count":4,"name":"american","url":"https://www.last.fm/tag/american"},{"count":3,"name":"r&b","url":"https://www.last.fm/tag/r&b"},{"count":3,"name":"50s","url":"https://www.last.fm/tag/50s"},{"count":3,"name":"gospel","url":"https://www.last.fm/tag/gospel"},{"count":3,"name":"female","url":"https://www.last.fm/tag/female"},{"count":2,"name":"legend","url":"https://www.last.fm/tag/legend"},{"count":2,"name":"rock","url":"https://www.last.fm/tag/rock"},{"count":2,"name":"easy listening","url":"https://www.last.fm/tag/easy+listening"},{"count":2,"name":"singer-songwriter","url":"https://www.last.fm/tag/singer-songwriter"},{"count":2,"name":"pop","url":"https://www.last.fm/tag/pop"},{"count":2,"name":"70s","url":"https://www.last.fm/tag/70s"},{"count":2,"name":"seen live","url":"https://www.last.fm/tag/seen+live"},{"count":2,"name":"funk","url":"https://www.last.fm/tag/funk"},{"count":2,"name":"jazzy","url":"https://www.last.fm/tag/jazzy"},{"count":2,"name":"Rock and Roll","url":"https://www.last.fm/tag/Rock+and+Roll"},{"count":2,"name":"USA","url":"https://www.last.fm/tag/USA"},{"count":2,"name":"diva","url":"https://www.last.fm/tag/diva"},{"count":2,"name":"at last","url":"https://www.last.fm/tag/at+last"},{"count":1,"name":"classic rock","url":"https://www.last.fm/tag/classic+rock"},{"count":1,"name":"classic","url":"https://www.last.fm/tag/classic"},{"count":1,"name":"female vocals","url":"https://www.last.fm/tag/female+vocals"},{"count":1,"name":"soul-blues","url":"https://www.last.fm/tag/soul-blues"},{"count":1,"name":"classic soul","url":"https://www.last.fm/tag/classic+soul"}],"@attr":{"artist":"Etta James"}}}