{"toptags":{"tag":[{"count":100,"name":"indie","url":"https://www.last.fm/tag/indie"},{"count":80,"name":"electronic","url":"https://www.last.fm/tag/electronic"},{"count":68,"name":"alternative","url":"https://www.last.fm/tag/alternative"},{"count":63,"name":"australian","url":"https://www.last.fm/tag/australian"},{"count":17,"name":"Aussie","url":"https://www.last.fm/tag/Aussie"},{"count":15,"name":"seen live","url":"https://www.last.fm/tag/seen+live"},{"count":10,"name":"indie pop","url":"https://www.last.fm/tag/indie+pop"},{"count":10,"name":"singer-songwriter","url":"https://www.last.fm/tag/singer-songwriter"},{"count":9,"name":"pop","url":"https://www.last.fm/tag/pop"},{"count":8,"name":"indie rock","url":"https://www.last.fm/tag/indie+rock"},{"count":7,"name":"experimental","url":"https://www.last.fm/tag/experimental"},{"count":6,"name":"male vocalists","url":"https://www.last.fm/tag/male+vocalists"},{"count":6,"name":"belgian","url":"https://www.last.fm/tag/belgian"},{"count":6,"name":"electronica","url":"https://www.last.fm/tag/electronica"},{"count":4,"name":"trip-hop","url":"https://www.last.fm/tag/trip-hop"},{"count":4,"name":"alternative rock","url":"https://www.last.fm/tag/alternative+rock"},{"count":4,"name":"chillout","url":"https://www.last.fm/tag/chillout"},{"count":4,"name":"gotye","url":"https://www.last.fm/tag/gotye"},{"count":3,"name":"downtempo","url":"https://www.last.fm/tag/downtempo"},{"count":3,"name":"rock","url":"https://www.last.fm/tag/rock"},{"count":2,"name":"trip hop","url":"https://www.last.fm/tag/trip+hop"},{"count":2,"name":"eclectic","url":"https://www.last.fm/tag/eclectic"},{"count":2,"name":"australia","url":"https://www.last.fm/tag/australia"},{"count":2,"name":"indietronica","url":"https://www.last.fm/tag/indietronica"},{"count":2,"name":"Belgium","url":"https://www.last.fm/tag/Belgium"},{"count":2,"name":"melbourne","url":"https://www.last.fm/tag/melbourne"},{"count":2,"name":"electro","url":"https://www.last.fm/tag/electro"},{"count":2,"name":"00s","url":"https://www.last.fm/tag/00s"},{"count":2,"name":"love at first listen","url":"https://www.last.fm/tag/love+at+first+listen"},{"count":2,"name":"art pop","url":"https://www.last.fm/tag/art+pop"},{"count":1,"name":"ambient","url":"https://www.last.fm/tag/ambient"}],"@attr":{"artist":"Gotye"}}}