{"toptags":{"tag":[{"count":100,"name":"new wave","url":"https://www.last.fm/tag/new+wave"},{"count":76,"name":"rock","url":"https://www.last.fm/tag/rock"},{"count":58,"name":"ex-yu","url":"https://www.last.fm/tag/ex-yu"},{"count":55,"name":"novi val","url":"https://www.last.fm/tag/novi+val"},{"count":49,"name":"ex-yu rock","url":"https://www.last.fm/tag/ex-yu+rock"},{"count":35,"name":"croatian","url":"https://www.last.fm/tag/croatian"},{"count":10,"name":"reggae","url":"https://www.last.fm/tag/reggae"},{"count":9,"name":"post-punk","url":"https://www.last.fm/tag/post-punk"},{"count":9,"name":"zagreb","url":"https://www.last.fm/tag/zagreb"},{"count":8,"name":"alternative rock","url":"https://www.last.fm/tag/alternative+rock"},{"count":7,"name":"ska","url":"https://www.last.fm/tag/ska"},{"count":7,"name":"balkan","url":"https://www.last.fm/tag/balkan"},{"count":5,"name":"Croatia","url":"https://www.last.fm/tag/Croatia"},{"count":5,"name":"domacica","url":"https://www.last.fm/tag/domacica"},{"count":5,"name":"haustor","url":"https://www.last.fm/tag/haustor"},{"count":3,"name":"alternative","url":"https://www.last.fm/tag/alternative"},{"count":3,"name":"horns","url":"https://www.last.fm/tag/horns"},{"count":3,"name":"Pop-Rock","url":"https://www.last.fm/tag/Pop-Rock"},{"count":3,"name":"Eastern Europe Rock","url":"https://www.last.fm/tag/Eastern+Europe+Rock"},{"count":3,"name":"serbian","url":"https://www.last.fm/tag/serbian"},{"count":3,"name":"balkan rock","url":"https://www.last.fm/tag/balkan+rock"},{"count":3,"name":"cro rock-novi val-ex YU i sl","url":"https://www.last.fm/tag/cro+rock-novi+val-ex+YU+i+sl"},{"count":2,"name":"seen live","url":"https://www.last.fm/tag/seen+live"},{"count":2,"name":"punk","url":"https://www.last.fm/tag/punk"},{"count":2,"name":"world","url":"https://www.last.fm/tag/world"},{"count":2,"name":"psychedelic","url":"https://www.last.fm/tag/psychedelic"},{"count":2,"name":"art rock","url":"https://www.last.fm/tag/art+rock"},{"count":2,"name":"World Music","url":"https://www.last.fm/tag/World+Music"},{"count":2,"name":"male vocalists","url":"https://www.last.fm/tag/male+vocalists"},{"count":2,"name":"Favorite","url":"https://www.last.fm/tag/Favorite"},{"count":2,"name":"sensual","url":"https://www.last.fm/tag/sensual"},{"count":2,"name":"two-tone","url":"https://www.last.fm/tag/two-tone"},{"count":2,"name":"Favourite bands","url":"https://www.last.fm/tag/Favourite+bands"},{"count":2,"name":"spotify","url":"https://www.last.fm/tag/spotify"},{"count":2,"name":"55","url":"https://www.last.fm/tag/55"},{"count":2,"name":"respect","url":"https://www.last.fm/tag/respect"},{"count":2,"name":"etno","url":"https://www.last.fm/tag/etno"},{"count":2,"name":"brutally perfect","url":"https://www.last.fm/tag/brutally+perfect"},{"count":2,"name":"novi talas","url":"https://www.last.fm/tag/novi+talas"},{"count":2,"name":"Domace","url":"https://www.last.fm/tag/Domace"},{"count":2,"name":"fenomenal","url":"https://www.last.fm/tag/fenomenal"},{"count":2,"name":"yu new wave","url":"https://www.last.fm/tag/yu+new+wave"},{"count":2,"name":"leiwand - muzyka","url":"https://www.last.fm/tag/leiwand+-+muzyka"},{"count":2,"name":"s-r-b-i-j-a","url":"https://www.last.fm/tag/s-r-b-i-j-a"},{"count":2,"name":"OpelMelange","url":"https://www.last.fm/tag/OpelMelange"},{"count":2,"name":"bogovski predobo","url":"https://www.last.fm/tag/bogovski+predobo"},{"count":2,"name":"jugonostalgija","url":"https://www.last.fm/tag/jugonostalgija"},{"count":2,"name":"only absence","url":"https://www.last.fm/tag/only+absence"},{"count":2,"name":"za kuliranje","url":"https://www.last.fm/tag/za+kuliranje"},{"count":2,"name":"za glupiranje","url":"https://www.last.fm/tag/za+glupiranje"},{"count":2,"name":"za uz rabota","url":"https://www.last.fm/tag/za+uz+rabota"},{"count":2,"name":"za u park so Vitach","url":"https://www.last.fm/tag/za+u+park+so+Vitach"},{"count":2,"name":"Richard There","url":"https://www.last.fm/tag/Richard+There"},{"count":2,"name":"rock hr","url":"https://www.last.fm/tag/rock+hr"}],"@attr":{"artist":"Haustor"}}}