{"toptags":{"tag":[{"count":100,"name":"Melodic Death Metal","url":"https://www.last.fm/tag/Melodic+Death+Metal"},{"count":28,"name":"death metal","url":"https://www.last.fm/tag/death+metal"},{"count":23,"name":"finnish","url":"https://www.last.fm/tag/finnish"},{"count":20,"name":"seen live","url":"https://www.last.fm/tag/seen+live"},{"count":15,"name":"metal","url":"https://www.last.fm/tag/metal"},{"count":10,"name":"finnish metal","url":"https://www.last.fm/tag/finnish+metal"},{"count":5,"name":"doom metal","url":"https://www.last.fm/tag/doom+metal"},{"count":2,"name":"Progressive metal","url":"https://www.last.fm/tag/Progressive+metal"},{"count":2,"name":"progressive death metal","url":"https://www.last.fm/tag/progressive+death+metal"},{"count":2,"name":"finland","url":"https://www.last.fm/tag/finland"},{"count":2,"name":"melodic death","url":"https://www.last.fm/tag/melodic+death"},{"count":2,"name":"melancholic","url":"https://www.last.fm/tag/melancholic"},{"count":2,"name":"melodic metal","url":"https://www.last.fm/tag/melodic+metal"},{"count":2,"name":"finnish melodic death metal","url":"https://www.last.fm/tag/finnish+melodic+death+metal"}],"@attr":{"artist":"Insomnium"}}}