{"toptags":{"tag":[{"count":100,"name":"ambient","url":"https://www.last.fm/tag/ambient"},{"count":80,"name":"electronic","url":"https://www.last.fm/tag/electronic"},{"count":57,"name":"downtempo","url":"https://www.last.fm/tag/downtempo"},{"count":49,"name":"chillout","url":"https://www.last.fm/tag/chillout"},{"count":32,"name":"electronica","url":"https://www.last.fm/tag/electronica"},{"count":31,"name":"seen live","url":"https://www.last.fm/tag/seen+live"},{"count":22,"name":"idm","url":"https://www.last.fm/tag/idm"},{"count":11,"name":"instrumental","url":"https://www.last.fm/tag/instrumental"},{"count":6,"name":"experimental","url":"https://www.last.fm/tag/experimental"},{"count":6,"name":"modern classical","url":"https://www.last.fm/tag/modern+classical"},{"count":6,"name":"british","url":"https://www.last.fm/tag/british"},{"count":5,"name":"microhouse","url":"https://www.last.fm/tag/microhouse"},{"count":5,"name":"piano","url":"https://www.last.fm/tag/piano"},{"count":5,"name":"glitch","url":"https://www.last.fm/tag/glitch"},{"count":5,"name":"neoclassical","url":"https://www.last.fm/tag/neoclassical"},{"count":4,"name":"modern composition","url":"https://www.last.fm/tag/modern+composition"},{"count":4,"name":"techno","url":"https://www.last.fm/tag/techno"},{"count":4,"name":"Soundtrack","url":"https://www.last.fm/tag/Soundtrack"},{"count":3,"name":"cinematic","url":"https://www.last.fm/tag/cinematic"},{"count":3,"name":"atmospheric","url":"https://www.last.fm/tag/atmospheric"},{"count":3,"name":"chill","url":"https://www.last.fm/tag/chill"},{"count":3,"name":"tech house","url":"https://www.last.fm/tag/tech+house"},{"count":3,"name":"contemporary classical","url":"https://www.last.fm/tag/contemporary+classical"},{"count":3,"name":"minimal","url":"https://www.last.fm/tag/minimal"},{"count":3,"name":"minimalism","url":"https://www.last.fm/tag/minimalism"},{"count":2,"name":"alternative","url":"https://www.last.fm/tag/alternative"},{"count":2,"name":"lounge","url":"https://www.last.fm/tag/lounge"},{"count":2,"name":"drone","url":"https://www.last.fm/tag/drone"},{"count":2,"name":"melancholic","url":"https://www.last.fm/tag/melancholic"},{"count":2,"name":"contemporary piano","url":"https://www.last.fm/tag/contemporary+piano"},{"count":2,"name":"minimal piano","url":"https://www.last.fm/tag/minimal+piano"},{"count":2,"name":"melancholy","url":"https://www.last.fm/tag/melancholy"},{"count":2,"name":"neo-classical","url":"https://www.last.fm/tag/neo-classical"},{"count":2,"name":"Experimental-Ambient","url":"https://www.last.fm/tag/Experimental-Ambient"},{"count":2,"name":"minimal ambient","url":"https://www.last.fm/tag/minimal+ambient"},{"count":2,"name":"minimalist","url":"https://www.last.fm/tag/minimalist"},{"count":2,"name":"post-classical","url":"https://www.last.fm/tag/post-classical"},{"count":2,"name":"piano ambient","url":"https://www.last.fm/tag/piano+ambient"},{"count":2,"name":"ambient piano","url":"https://www.last.fm/tag/ambient+piano"},{"count":2,"name":"dark ambient","url":"https://www.last.fm/tag/dark+ambient"},{"count":2,"name":"House","url":"https://www.last.fm/tag/House"},{"count":2,"name":"beautiful","url":"https://www.last.fm/tag/beautiful"},{"count":2,"name":"relax","url":"https://www.last.fm/tag/relax"},{"count":2,"name":"indie","url":"https://www.last.fm/tag/indie"},{"count":2,"name":"UK","url":"https://www.last.fm/tag/UK"},{"count":2,"name":"london","url":"https://www.last.fm/tag/london"},{"count":2,"name":"Sleep","url":"https://www.last.fm/tag/Sleep"},{"count":2,"name":"Ambient Techno","url":"https://www.last.fm/tag/Ambient+Techno"},{"count":2,"name":"jon hopkins","url":"https://www.last.fm/tag/jon+hopkins"},{"count":1,"name":"minimal techno","url":"https://www.last.fm/tag/minimal+techno"},{"count":1,"name":"soundscape","url":"https://www.last.fm/tag/soundscape"},{"count":1,"name":"space music","url":"https://www.last.fm/tag/space+music"},{"count":1,"name":"00s","url":"https://www.last.fm/tag/00s"}],"@attr":{"artist":"Jon Hopkins"}}}