{"toptags":{"tag":[{"count":100,"name":"rnb","url":"https://www.last.fm/tag/rnb"},{"count":88,"name":"soul","url":"https://www.last.fm/tag/soul"},{"count":49,"name":"r&b","url":"https://www.last.fm/tag/r&b"},{"count":46,"name":"female vocalist","url":"https://www.last.fm/tag/female+vocalist"},{"count":31,"name":"female vocalists","url":"https://www.last.fm/tag/female+vocalists"},{"count":19,"name":"Hip-Hop","url":"https://www.last.fm/tag/Hip-Hop"},{"count":16,"name":"urban","url":"https://www.last.fm/tag/urban"},{"count":10,"name":"hip hop","url":"https://www.last.fm/tag/hip+hop"},{"count":10,"name":"pop","url":"https://www.last.fm/tag/pop"},{"count":10,"name":"underrated","url":"https://www.last.fm/tag/underrated"},{"count":10,"name":"real talk","url":"https://www.last.fm/tag/real+talk"},{"count":7,"name":"rap","url":"https://www.last.fm/tag/rap"},{"count":7,"name":"memphis","url":"https://www.last.fm/tag/memphis"},{"count":7,"name":"10s","url":"https://www.last.fm/tag/10s"},{"count":7,"name":"All","url":"https://www.last.fm/tag/All"},{"count":7,"name":"K Michelle","url":"https://www.last.fm/tag/K+Michelle"},{"count":4,"name":"singer-songwriter","url":"https://www.last.fm/tag/singer-songwriter"},{"count":4,"name":"american","url":"https://www.last.fm/tag/american"},{"count":4,"name":"nu soul","url":"https://www.last.fm/tag/nu+soul"},{"count":4,"name":"1","url":"https://www.last.fm/tag/1"},{"count":4,"name":"r and b","url":"https://www.last.fm/tag/r+and+b"},{"count":4,"name":"love songs","url":"https://www.last.fm/tag/love+songs"},{"count":4,"name":"strong","url":"https://www.last.fm/tag/strong"},{"count":4,"name":"rhythm and blues","url":"https://www.last.fm/tag/rhythm+and+blues"},{"count":4,"name":"00s","url":"https://www.last.fm/tag/00s"},{"count":4,"name":"Birthday","url":"https://www.last.fm/tag/Birthday"},{"count":4,"name":"Neo-Soul","url":"https://www.last.fm/tag/Neo-Soul"},{"count":4,"name":"2010s","url":"https://www.last.fm/tag/2010s"},{"count":4,"name":"Tennessee","url":"https://www.last.fm/tag/Tennessee"},{"count":4,"name":"vh1","url":"https://www.last.fm/tag/vh1"},{"count":4,"name":"female rap","url":"https://www.last.fm/tag/female+rap"},{"count":4,"name":"female rapper","url":"https://www.last.fm/tag/female+rapper"},{"count":4,"name":"rhythum and blues tag","url":"https://www.last.fm/tag/rhythum+and+blues+tag"},{"count":4,"name":"femc","url":"https://www.last.fm/tag/femc"},{"count":4,"name":"sweet vocals","url":"https://www.last.fm/tag/sweet+vocals"},{"count":4,"name":"Soul Diva","url":"https://www.last.fm/tag/Soul+Diva"},{"count":4,"name":"reality star","url":"https://www.last.fm/tag/reality+star"},{"count":4,"name":"myhiphop","url":"https://www.last.fm/tag/myhiphop"},{"count":4,"name":"excellent singer","url":"https://www.last.fm/tag/excellent+singer"},{"count":4,"name":"Wie alles begann","url":"https://www.last.fm/tag/Wie+alles+begann"},{"count":4,"name":"Less Known Artist","url":"https://www.last.fm/tag/Less+Known+Artist"},{"count":4,"name":"love her songs","url":"https://www.last.fm/tag/love+her+songs"},{"count":4,"name":"MrsChocolateGur","url":"https://www.last.fm/tag/MrsChocolateGur"},{"count":4,"name":"truthfulness","url":"https://www.last.fm/tag/truthfulness"}],"@attr":{"artist":"K. Michelle"}}}