{"toptags":{"tag":[{"count":100,"name":"House","url":"https://www.last.fm/tag/House"},{"count":67,"name":"electronic","url":"https://www.last.fm/tag/electronic"},{"count":54,"name":"deep house","url":"https://www.last.fm/tag/deep+house"},{"count":45,"name":"chillout","url":"https://www.last.fm/tag/chillout"},{"count":44,"name":"dance","url":"https://www.last.fm/tag/dance"},{"count":11,"name":"lounge","url":"https://www.last.fm/tag/lounge"},{"count":9,"name":"seen live","url":"https://www.last.fm/tag/seen+live"},{"count":9,"name":"electronica","url":"https://www.last.fm/tag/electronica"},{"count":8,"name":"Kaskade","url":"https://www.last.fm/tag/Kaskade"},{"count":7,"name":"Progressive House","url":"https://www.last.fm/tag/Progressive+House"},{"count":6,"name":"trance","url":"https://www.last.fm/tag/trance"},{"count":6,"name":"vocal house","url":"https://www.last.fm/tag/vocal+house"},{"count":5,"name":"american","url":"https://www.last.fm/tag/american"},{"count":4,"name":"electro house","url":"https://www.last.fm/tag/electro+house"},{"count":3,"name":"downtempo","url":"https://www.last.fm/tag/downtempo"},{"count":3,"name":"female vocalists","url":"https://www.last.fm/tag/female+vocalists"},{"count":3,"name":"dj","url":"https://www.last.fm/tag/dj"},{"count":3,"name":"chill","url":"https://www.last.fm/tag/chill"},{"count":3,"name":"electro","url":"https://www.last.fm/tag/electro"},{"count":3,"name":"Progressive","url":"https://www.last.fm/tag/Progressive"},{"count":3,"name":"club","url":"https://www.last.fm/tag/club"},{"count":3,"name":"Om Records","url":"https://www.last.fm/tag/Om+Records"},{"count":2,"name":"san francisco","url":"https://www.last.fm/tag/san+francisco"},{"count":2,"name":"funky house","url":"https://www.last.fm/tag/funky+house"},{"count":2,"name":"trip-hop","url":"https://www.last.fm/tag/trip-hop"},{"count":2,"name":"alternative","url":"https://www.last.fm/tag/alternative"},{"count":2,"name":"ambient","url":"https://www.last.fm/tag/ambient"},{"count":2,"name":"techno","url":"https://www.last.fm/tag/techno"},{"count":2,"name":"pop","url":"https://www.last.fm/tag/pop"},{"count":2,"name":"Very good House","url":"https://www.last.fm/tag/Very+good+House"},{"count":2,"name":"indie","url":"https://www.last.fm/tag/indie"},{"count":1,"name":"groove","url":"https://www.last.fm/tag/groove"},{"count":1,"name":"vocal trance","url":"https://www.last.fm/tag/vocal+trance"},{"count":1,"name":"Soulful house","url":"https://www.last.fm/tag/Soulful+house"},{"count":1,"name":"deephouse","url":"https://www.last.fm/tag/deephouse"},{"count":1,"name":"Chill House","url":"https://www.last.fm/tag/Chill+House"},{"count":1,"name":"My promising artists","url":"https://www.last.fm/tag/My+promising+artists"}],"@attr":{"artist":"Kaskade"}}}