{"toptags":{"tag":[{"count":100,"name":"one direction","url":"https://www.last.fm/tag/one+direction"},{"count":91,"name":"pop","url":"https://www.last.fm/tag/pop"},{"count":91,"name":"irish","url":"https://www.last.fm/tag/irish"},{"count":82,"name":"niall horan","url":"https://www.last.fm/tag/niall+horan"},{"count":46,"name":"cute","url":"https://www.last.fm/tag/cute"},{"count":46,"name":"baby","url":"https://www.last.fm/tag/baby"},{"count":28,"name":"folk","url":"https://www.last.fm/tag/folk"},{"count":28,"name":"gay","url":"https://www.last.fm/tag/gay"},{"count":28,"name":"FAGGOT","url":"https://www.last.fm/tag/FAGGOT"},{"count":28,"name":"fag","url":"https://www.last.fm/tag/fag"},{"count":19,"name":"sexy","url":"https://www.last.fm/tag/sexy"},{"count":19,"name":"singer-songwriter","url":"https://www.last.fm/tag/singer-songwriter"},{"count":19,"name":"acoustic","url":"https://www.last.fm/tag/acoustic"},{"count":19,"name":"male vocalists","url":"https://www.last.fm/tag/male+vocalists"},{"count":19,"name":"liam payne","url":"https://www.last.fm/tag/liam+payne"},{"count":10,"name":"british","url":"https://www.last.fm/tag/british"},{"count":10,"name":"pop rock","url":"https://www.last.fm/tag/pop+rock"},{"count":10,"name":"under 2000 listeners","url":"https://www.last.fm/tag/under+2000+listeners"},{"count":10,"name":"hilarious","url":"https://www.last.fm/tag/hilarious"},{"count":10,"name":"boyband","url":"https://www.last.fm/tag/boyband"},{"count":10,"name":"inspiring","url":"https://www.last.fm/tag/inspiring"},{"count":10,"name":"perfecto","url":"https://www.last.fm/tag/perfecto"},{"count":10,"name":"talented","url":"https://www.last.fm/tag/talented"},{"count":10,"name":"guys I would fuck","url":"https://www.last.fm/tag/guys+I+would+fuck"},{"count":10,"name":"Sexy Boy","url":"https://www.last.fm/tag/Sexy+Boy"},{"count":10,"name":"X factor","url":"https://www.last.fm/tag/X+factor"},{"count":10,"name":"Just Amazing","url":"https://www.last.fm/tag/Just+Amazing"},{"count":10,"name":"melhor banda","url":"https://www.last.fm/tag/melhor+banda"},{"count":10,"name":"harry styles","url":"https://www.last.fm/tag/harry+styles"},{"count":10,"name":"zayn","url":"https://www.last.fm/tag/zayn"},{"count":10,"name":"louis tomlinson","url":"https://www.last.fm/tag/louis+tomlinson"}],"@attr":{"artist":"Niall Horan"}}}