{"toptags":{"tag":[{"count":100,"name":"deep house","url":"https://www.last.fm/tag/deep+house"},{"count":59,"name":"House","url":"https://www.last.fm/tag/House"},{"count":58,"name":"seen live","url":"https://www.last.fm/tag/seen+live"},{"count":52,"name":"minimal","url":"https://www.last.fm/tag/minimal"},{"count":50,"name":"techno","url":"https://www.last.fm/tag/techno"},{"count":45,"name":"electronic","url":"https://www.last.fm/tag/electronic"},{"count":15,"name":"tech house","url":"https://www.last.fm/tag/tech+house"},{"count":15,"name":"russian","url":"https://www.last.fm/tag/russian"},{"count":11,"name":"minimal techno","url":"https://www.last.fm/tag/minimal+techno"},{"count":9,"name":"Russia","url":"https://www.last.fm/tag/Russia"},{"count":8,"name":"ambient","url":"https://www.last.fm/tag/ambient"},{"count":8,"name":"female vocalists","url":"https://www.last.fm/tag/female+vocalists"},{"count":8,"name":"nina kraviz","url":"https://www.last.fm/tag/nina+kraviz"},{"count":6,"name":"electronica","url":"https://www.last.fm/tag/electronica"},{"count":6,"name":"deep","url":"https://www.last.fm/tag/deep"},{"count":6,"name":"ms kraviz","url":"https://www.last.fm/tag/ms+kraviz"},{"count":5,"name":"chillout","url":"https://www.last.fm/tag/chillout"},{"count":5,"name":"experimental","url":"https://www.last.fm/tag/experimental"},{"count":5,"name":"electro","url":"https://www.last.fm/tag/electro"},{"count":5,"name":"microhouse","url":"https://www.last.fm/tag/microhouse"},{"count":5,"name":"russian deep","url":"https://www.last.fm/tag/russian+deep"},{"count":5,"name":"russian deep girl","url":"https://www.last.fm/tag/russian+deep+girl"},{"count":3,"name":"trip-hop","url":"https://www.last.fm/tag/trip-hop"},{"count":3,"name":"indie","url":"https://www.last.fm/tag/indie"},{"count":3,"name":"downtempo","url":"https://www.last.fm/tag/downtempo"},{"count":3,"name":"dance","url":"https://www.last.fm/tag/dance"},{"count":3,"name":"hot","url":"https://www.last.fm/tag/hot"},{"count":3,"name":"10s","url":"https://www.last.fm/tag/10s"},{"count":3,"name":"seen live 2010","url":"https://www.last.fm/tag/seen+live+2010"},{"count":3,"name":"deep music","url":"https://www.last.fm/tag/deep+music"},{"count":3,"name":"kraviz","url":"https://www.last.fm/tag/kraviz"},{"count":3,"name":"jus-ed","url":"https://www.last.fm/tag/jus-ed"},{"count":2,"name":"female","url":"https://www.last.fm/tag/female"},{"count":2,"name":"soul","url":"https://www.last.fm/tag/soul"},{"count":2,"name":"alternative","url":"https://www.last.fm/tag/alternative"},{"count":2,"name":"folk","url":"https://www.last.fm/tag/folk"},{"count":2,"name":"sexy","url":"https://www.last.fm/tag/sexy"},{"count":2,"name":"singer-songwriter","url":"https://www.last.fm/tag/singer-songwriter"},{"count":2,"name":"dubstep","url":"https://www.last.fm/tag/dubstep"},{"count":2,"name":"C","url":"https://www.last.fm/tag/C"},{"count":2,"name":"Love","url":"https://www.last.fm/tag/Love"},{"count":2,"name":"funk","url":"https://www.last.fm/tag/funk"},{"count":2,"name":"fantastic","url":"https://www.last.fm/tag/fantastic"},{"count":2,"name":"beautiful","url":"https://www.last.fm/tag/beautiful"},{"count":2,"name":"girls","url":"https://www.last.fm/tag/girls"},{"count":2,"name":"3","url":"https://www.last.fm/tag/3"},{"count":2,"name":"Acid","url":"https://www.last.fm/tag/Acid"},{"count":2,"name":"dub techno","url":"https://www.last.fm/tag/dub+techno"},{"count":2,"name":"g","url":"https://www.last.fm/tag/g"},{"count":2,"name":"pretty","url":"https://www.last.fm/tag/pretty"},{"count":2,"name":"k","url":"https://www.last.fm/tag/k"},{"count":2,"name":"1","url":"https://www.last.fm/tag/1"},{"count":2,"name":"f","url":"https://www.last.fm/tag/f"},{"count":2,"name":"the ladies that should sit on my sofa or somewhere else in my flat because they are darlings and oh so lovely","url":"https://www.last.fm/tag/the+ladies+that+should+sit+on+my+sofa+or+somewhere+else+in+my+flat+because+they+are+darlings+and+oh+so+lovely"},{"count":2,"name":"dj","url":"https://www.last.fm/tag/dj"},{"count":2,"name":"tech-house","url":"https://www.last.fm/tag/tech-house"},{"count":2,"name":"j","url":"https://www.last.fm/tag/j"},{"count":2,"name":"2011","url":"https://www.last.fm/tag/2011"},{"count":2,"name":"4","url":"https://www.last.fm/tag/4"},{"count":2,"name":"producer","url":"https://www.last.fm/tag/producer"},{"count":2,"name":"R","url":"https://www.last.fm/tag/R"},{"count":2,"name":"pleasant","url":"https://www.last.fm/tag/pleasant"},{"count":2,"name":"Ambient Techno","url":"https://www.last.fm/tag/Ambient+Techno"},{"count":2,"name":"lovely","url":"https://www.last.fm/tag/lovely"},{"count":2,"name":"visual","url":"https://www.last.fm/tag/visual"},{"count":2,"name":"to listen","url":"https://www.last.fm/tag/to+listen"},{"count":2,"name":"frauen und technik","url":"https://www.last.fm/tag/frauen+und+technik"},{"count":2,"name":"women","url":"https://www.last.fm/tag/women"},{"count":2,"name":"lost","url":"https://www.last.fm/tag/lost"},{"count":2,"name":"E","url":"https://www.last.fm/tag/E"},{"count":2,"name":"woman","url":"https://www.last.fm/tag/woman"},{"count":2,"name":"i love her","url":"https://www.last.fm/tag/i+love+her"},{"count":2,"name":"misc","url":"https://www.last.fm/tag/misc"},{"count":2,"name":"9","url":"https://www.last.fm/tag/9"},{"count":2,"name":"2","url":"https://www.last.fm/tag/2"},{"count":2,"name":"7","url":"https://www.last.fm/tag/7"},{"count":2,"name":"Girl","url":"https://www.last.fm/tag/Girl"},{"count":2,"name":"Pleasing","url":"https://www.last.fm/tag/Pleasing"},{"count":2,"name":"babe","url":"https://www.last.fm/tag/babe"},{"count":2,"name":"5","url":"https://www.last.fm/tag/5"},{"count":2,"name":"ladies","url":"https://www.last.fm/tag/ladies"},{"count":2,"name":"6","url":"https://www.last.fm/tag/6"},{"count":2,"name":"i","url":"https://www.last.fm/tag/i"},{"count":2,"name":"Richard","url":"https://www.last.fm/tag/Richard"},{"count":2,"name":"o","url":"https://www.last.fm/tag/o"},{"count":2,"name":"8","url":"https://www.last.fm/tag/8"},{"count":2,"name":"0","url":"https://www.last.fm/tag/0"},{"count":2,"name":"thoughts","url":"https://www.last.fm/tag/thoughts"},{"count":2,"name":"bananas","url":"https://www.last.fm/tag/bananas"},{"count":2,"name":"x","url":"https://www.last.fm/tag/x"},{"count":2,"name":"bats","url":"https://www.last.fm/tag/bats"},{"count":2,"name":"2015","url":"https://www.last.fm/tag/2015"},{"count":2,"name":"djs","url":"https://www.last.fm/tag/djs"},{"count":2,"name":"variable","url":"https://www.last.fm/tag/variable"},{"count":2,"name":"Miscellaneous","url":"https://www.last.fm/tag/Miscellaneous"},{"count":2,"name":"ghetto tech","url":"https://www.last.fm/tag/ghetto+tech"},{"count":2,"name":"All","url":"https://www.last.fm/tag/All"},{"count":2,"name":"Tasty","url":"https://www.last.fm/tag/Tasty"},{"count":2,"name":"Elettronica","url":"https://www.last.fm/tag/Elettronica"},{"count":2,"name":"d","url":"https://www.last.fm/tag/d"}],"@attr":{"artist":"Nina Kraviz"}}}