{"toptags":{"tag":[{"count":100,"name":"Progressive metal","url":"https://www.last.fm/tag/Progressive+metal"},{"count":65,"name":"folk metal","url":"https://www.last.fm/tag/folk+metal"},{"count":54,"name":"oriental metal","url":"https://www.last.fm/tag/oriental+metal"},{"count":35,"name":"progressive death metal","url":"https://www.last.fm/tag/progressive+death+metal"},{"count":34,"name":"death metal","url":"https://www.last.fm/tag/death+metal"},{"count":21,"name":"seen live","url":"https://www.last.fm/tag/seen+live"},{"count":20,"name":"metal","url":"https://www.last.fm/tag/metal"},{"count":14,"name":"israeli","url":"https://www.last.fm/tag/israeli"},{"count":13,"name":"doom metal","url":"https://www.last.fm/tag/doom+metal"},{"count":7,"name":"Israel","url":"https://www.last.fm/tag/Israel"},{"count":6,"name":"Progressive","url":"https://www.last.fm/tag/Progressive"},{"count":4,"name":"Oriental","url":"https://www.last.fm/tag/Oriental"},{"count":4,"name":"Melodic Death Metal","url":"https://www.last.fm/tag/Melodic+Death+Metal"},{"count":4,"name":"folk","url":"https://www.last.fm/tag/folk"},{"count":3,"name":"Progressive Folk Metal","url":"https://www.last.fm/tag/Progressive+Folk+Metal"},{"count":3,"name":"israeli metal","url":"https://www.last.fm/tag/israeli+metal"},{"count":3,"name":"Middle Eastern Folk Metal","url":"https://www.last.fm/tag/Middle+Eastern+Folk+Metal"},{"count":3,"name":"jewish","url":"https://www.last.fm/tag/jewish"},{"count":2,"name":"hebrew","url":"https://www.last.fm/tag/hebrew"},{"count":2,"name":"Progressive rock","url":"https://www.last.fm/tag/Progressive+rock"},{"count":2,"name":"Middle Eastern","url":"https://www.last.fm/tag/Middle+Eastern"},{"count":2,"name":"heavy metal","url":"https://www.last.fm/tag/heavy+metal"},{"count":2,"name":"Death Doom Metal","url":"https://www.last.fm/tag/Death+Doom+Metal"},{"count":2,"name":"symphonic metal","url":"https://www.last.fm/tag/symphonic+metal"},{"count":2,"name":"rock","url":"https://www.last.fm/tag/rock"},{"count":2,"name":"prog metal","url":"https://www.last.fm/tag/prog+metal"},{"count":1,"name":"Doom","url":"https://www.last.fm/tag/Doom"},{"count":1,"name":"oriental progressive metal","url":"https://www.last.fm/tag/oriental+progressive+metal"},{"count":1,"name":"prog","url":"https://www.last.fm/tag/prog"},{"count":1,"name":"death-doom metal","url":"https://www.last.fm/tag/death-doom+metal"}],"@attr":{"artist":"Orphaned Land"}}}