{"toptags":{"tag":[{"count":100,"name":"rnb","url":"https://www.last.fm/tag/rnb"},{"count":78,"name":"r&b","url":"https://www.last.fm/tag/r&b"},{"count":62,"name":"soul","url":"https://www.last.fm/tag/soul"},{"count":55,"name":"Hip-Hop","url":"https://www.last.fm/tag/Hip-Hop"},{"count":26,"name":"canada","url":"https://www.last.fm/tag/canada"},{"count":13,"name":"Canadian","url":"https://www.last.fm/tag/Canadian"},{"count":13,"name":"ovo","url":"https://www.last.fm/tag/ovo"},{"count":10,"name":"hip hop","url":"https://www.last.fm/tag/hip+hop"},{"count":10,"name":"rap","url":"https://www.last.fm/tag/rap"},{"count":7,"name":"hiphop","url":"https://www.last.fm/tag/hiphop"},{"count":7,"name":"contemporary rnb","url":"https://www.last.fm/tag/contemporary+rnb"},{"count":7,"name":"alternative rnb","url":"https://www.last.fm/tag/alternative+rnb"},{"count":7,"name":"prog-rnb","url":"https://www.last.fm/tag/prog-rnb"},{"count":7,"name":"pbrnb","url":"https://www.last.fm/tag/pbrnb"},{"count":7,"name":"future sound-alike","url":"https://www.last.fm/tag/future+sound-alike"},{"count":4,"name":"electronic","url":"https://www.last.fm/tag/electronic"},{"count":4,"name":"seen live","url":"https://www.last.fm/tag/seen+live"},{"count":4,"name":"pop","url":"https://www.last.fm/tag/pop"},{"count":4,"name":"chill","url":"https://www.last.fm/tag/chill"},{"count":4,"name":"synth pop","url":"https://www.last.fm/tag/synth+pop"},{"count":4,"name":"techno","url":"https://www.last.fm/tag/techno"},{"count":4,"name":"Experimental pop","url":"https://www.last.fm/tag/Experimental+pop"},{"count":4,"name":"party","url":"https://www.last.fm/tag/party"},{"count":4,"name":"male vocalists","url":"https://www.last.fm/tag/male+vocalists"},{"count":4,"name":"Neo-Soul","url":"https://www.last.fm/tag/Neo-Soul"},{"count":4,"name":"weed","url":"https://www.last.fm/tag/weed"},{"count":4,"name":"next","url":"https://www.last.fm/tag/next"},{"count":4,"name":"r'n'b","url":"https://www.last.fm/tag/r%27n%27b"},{"count":4,"name":"All","url":"https://www.last.fm/tag/All"},{"count":4,"name":"try","url":"https://www.last.fm/tag/try"},{"count":4,"name":"elecronic","url":"https://www.last.fm/tag/elecronic"},{"count":4,"name":"later","url":"https://www.last.fm/tag/later"},{"count":4,"name":"ish","url":"https://www.last.fm/tag/ish"},{"count":4,"name":"door","url":"https://www.last.fm/tag/door"},{"count":4,"name":"experimental rnb","url":"https://www.last.fm/tag/experimental+rnb"},{"count":4,"name":"musical journey to the ends of time","url":"https://www.last.fm/tag/musical+journey+to+the+ends+of+time"},{"count":4,"name":"dark rnb","url":"https://www.last.fm/tag/dark+rnb"},{"count":4,"name":"NC 50","url":"https://www.last.fm/tag/NC+50"},{"count":4,"name":"PC 25","url":"https://www.last.fm/tag/PC+25"},{"count":4,"name":"NC 25","url":"https://www.last.fm/tag/NC+25"},{"count":4,"name":"Octobers Very Own","url":"https://www.last.fm/tag/Octobers+Very+Own"},{"count":4,"name":"partynextdoor","url":"https://www.last.fm/tag/partynextdoor"},{"count":4,"name":"gayjay","url":"https://www.last.fm/tag/gayjay"},{"count":4,"name":"party next door","url":"https://www.last.fm/tag/party+next+door"}],"@attr":{"artist":"PARTYNEXTDOOR"}}}