{"toptags":{"tag":[{"count":100,"name":"Progressive rock","url":"https://www.last.fm/tag/Progressive+rock"},{"count":32,"name":"Progressive metal","url":"https://www.last.fm/tag/Progressive+metal"},{"count":27,"name":"psychedelic","url":"https://www.last.fm/tag/psychedelic"},{"count":25,"name":"Progressive","url":"https://www.last.fm/tag/Progressive"},{"count":24,"name":"rock","url":"https://www.last.fm/tag/rock"},{"count":18,"name":"seen live","url":"https://www.last.fm/tag/seen+live"},{"count":10,"name":"Psychedelic Rock","url":"https://www.last.fm/tag/Psychedelic+Rock"},{"count":9,"name":"british","url":"https://www.last.fm/tag/british"},{"count":8,"name":"alternative","url":"https://www.last.fm/tag/alternative"},{"count":4,"name":"experimental","url":"https://www.last.fm/tag/experimental"},{"count":4,"name":"alternative rock","url":"https://www.last.fm/tag/alternative+rock"},{"count":4,"name":"metal","url":"https://www.last.fm/tag/metal"},{"count":3,"name":"ambient","url":"https://www.last.fm/tag/ambient"},{"count":3,"name":"space rock","url":"https://www.last.fm/tag/space+rock"},{"count":3,"name":"prog rock","url":"https://www.last.fm/tag/prog+rock"},{"count":3,"name":"art rock","url":"https://www.last.fm/tag/art+rock"},{"count":3,"name":"steven wilson","url":"https://www.last.fm/tag/steven+wilson"},{"count":2,"name":"porcupine tree","url":"https://www.last.fm/tag/porcupine+tree"},{"count":2,"name":"prog","url":"https://www.last.fm/tag/prog"},{"count":2,"name":"atmospheric","url":"https://www.last.fm/tag/atmospheric"},{"count":2,"name":"post-rock","url":"https://www.last.fm/tag/post-rock"},{"count":2,"name":"Experimental Rock","url":"https://www.last.fm/tag/Experimental+Rock"},{"count":2,"name":"melancholic","url":"https://www.last.fm/tag/melancholic"},{"count":1,"name":"UK","url":"https://www.last.fm/tag/UK"},{"count":1,"name":"hard rock","url":"https://www.last.fm/tag/hard+rock"}],"@attr":{"artist":"Porcupine Tree"}}}