{"toptags":{"tag":[{"count":100,"name":"dancehall","url":"https://www.last.fm/tag/dancehall"},{"count":94,"name":"reggae","url":"https://www.last.fm/tag/reggae"},{"count":61,"name":"Hip-Hop","url":"https://www.last.fm/tag/Hip-Hop"},{"count":39,"name":"rnb","url":"https://www.last.fm/tag/rnb"},{"count":35,"name":"rap","url":"https://www.last.fm/tag/rap"},{"count":13,"name":"hip hop","url":"https://www.last.fm/tag/hip+hop"},{"count":11,"name":"dance","url":"https://www.last.fm/tag/dance"},{"count":11,"name":"Sean Paul","url":"https://www.last.fm/tag/Sean+Paul"},{"count":10,"name":"seen live","url":"https://www.last.fm/tag/seen+live"},{"count":9,"name":"pop","url":"https://www.last.fm/tag/pop"},{"count":7,"name":"jamaica","url":"https://www.last.fm/tag/jamaica"},{"count":7,"name":"ragga","url":"https://www.last.fm/tag/ragga"},{"count":7,"name":"jamaican","url":"https://www.last.fm/tag/jamaican"},{"count":5,"name":"Reggaeton","url":"https://www.last.fm/tag/Reggaeton"},{"count":4,"name":"male vocalists","url":"https://www.last.fm/tag/male+vocalists"},{"count":2,"name":"hiphop","url":"https://www.last.fm/tag/hiphop"},{"count":2,"name":"rock","url":"https://www.last.fm/tag/rock"},{"count":2,"name":"electronic","url":"https://www.last.fm/tag/electronic"},{"count":2,"name":"soul","url":"https://www.last.fm/tag/soul"},{"count":2,"name":"00s","url":"https://www.last.fm/tag/00s"},{"count":2,"name":"alternative","url":"https://www.last.fm/tag/alternative"},{"count":2,"name":"r&b","url":"https://www.last.fm/tag/r&b"},{"count":2,"name":"dancehall reggae","url":"https://www.last.fm/tag/dancehall+reggae"},{"count":2,"name":"electronica","url":"https://www.last.fm/tag/electronica"},{"count":2,"name":"dance hall","url":"https://www.last.fm/tag/dance+hall"},{"count":1,"name":"urban","url":"https://www.last.fm/tag/urban"}],"@attr":{"artist":"Sean Paul"}}}