{"toptags":{"tag":[{"count":100,"name":"rap","url":"https://www.last.fm/tag/rap"},{"count":92,"name":"french","url":"https://www.last.fm/tag/french"},{"count":71,"name":"Hip-Hop","url":"https://www.last.fm/tag/Hip-Hop"},{"count":59,"name":"French hip hop","url":"https://www.last.fm/tag/French+hip+hop"},{"count":19,"name":"hip hop","url":"https://www.last.fm/tag/hip+hop"},{"count":13,"name":"rap francais","url":"https://www.last.fm/tag/rap+francais"},{"count":13,"name":"homophobe","url":"https://www.last.fm/tag/homophobe"},{"count":9,"name":"homophobic","url":"https://www.last.fm/tag/homophobic"},{"count":9,"name":"french hip-hop","url":"https://www.last.fm/tag/french+hip-hop"},{"count":9,"name":"rap conscient","url":"https://www.last.fm/tag/rap+conscient"},{"count":7,"name":"france","url":"https://www.last.fm/tag/france"},{"count":7,"name":"Français","url":"https://www.last.fm/tag/Fran%C3%A7ais"},{"count":7,"name":"french rap","url":"https://www.last.fm/tag/french+rap"},{"count":7,"name":"worst of 2010","url":"https://www.last.fm/tag/worst+of+2010"},{"count":7,"name":"Rap FR","url":"https://www.last.fm/tag/Rap+FR"},{"count":5,"name":"seen live","url":"https://www.last.fm/tag/seen+live"},{"count":5,"name":"underground hip-hop","url":"https://www.last.fm/tag/underground+hip-hop"},{"count":5,"name":"folklore intellectuel","url":"https://www.last.fm/tag/folklore+intellectuel"},{"count":5,"name":"bouse auditive","url":"https://www.last.fm/tag/bouse+auditive"},{"count":5,"name":"Hall Of Shame","url":"https://www.last.fm/tag/Hall+Of+Shame"},{"count":3,"name":"pop","url":"https://www.last.fm/tag/pop"},{"count":3,"name":"dance","url":"https://www.last.fm/tag/dance"},{"count":3,"name":"xxx","url":"https://www.last.fm/tag/xxx"},{"count":3,"name":"comedy","url":"https://www.last.fm/tag/comedy"},{"count":3,"name":"under 2000 listeners","url":"https://www.last.fm/tag/under+2000+listeners"},{"count":3,"name":"lol","url":"https://www.last.fm/tag/lol"},{"count":3,"name":"2000","url":"https://www.last.fm/tag/2000"},{"count":3,"name":"paris","url":"https://www.last.fm/tag/paris"},{"count":3,"name":"75","url":"https://www.last.fm/tag/75"},{"count":3,"name":"Gay Metal","url":"https://www.last.fm/tag/Gay+Metal"},{"count":3,"name":"All","url":"https://www.last.fm/tag/All"},{"count":3,"name":"nazi","url":"https://www.last.fm/tag/nazi"},{"count":3,"name":"hip","url":"https://www.last.fm/tag/hip"},{"count":3,"name":"hop","url":"https://www.last.fm/tag/hop"},{"count":3,"name":"Great album","url":"https://www.last.fm/tag/Great+album"},{"count":3,"name":"worst music ever","url":"https://www.last.fm/tag/worst+music+ever"},{"count":3,"name":"spotify","url":"https://www.last.fm/tag/spotify"},{"count":3,"name":"french humour","url":"https://www.last.fm/tag/french+humour"},{"count":3,"name":"ridicule","url":"https://www.last.fm/tag/ridicule"},{"count":3,"name":"Rechtsrock","url":"https://www.last.fm/tag/Rechtsrock"},{"count":3,"name":"aiight","url":"https://www.last.fm/tag/aiight"},{"count":3,"name":"SYL","url":"https://www.last.fm/tag/SYL"},{"count":3,"name":"tristesse","url":"https://www.last.fm/tag/tristesse"},{"count":3,"name":"6 stars","url":"https://www.last.fm/tag/6+stars"},{"count":3,"name":"sexion","url":"https://www.last.fm/tag/sexion"},{"count":3,"name":"homophobia","url":"https://www.last.fm/tag/homophobia"},{"count":3,"name":"1 star","url":"https://www.last.fm/tag/1+star"},{"count":3,"name":"this shit is killing hip hop","url":"https://www.last.fm/tag/this+shit+is+killing+hip+hop"},{"count":3,"name":"sniper","url":"https://www.last.fm/tag/sniper"},{"count":3,"name":"merde","url":"https://www.last.fm/tag/merde"},{"count":3,"name":"De la merde","url":"https://www.last.fm/tag/De+la+merde"},{"count":3,"name":"seen live more than one time","url":"https://www.last.fm/tag/seen+live+more+than+one+time"},{"count":3,"name":"xptdr","url":"https://www.last.fm/tag/xptdr"},{"count":3,"name":"analphabete","url":"https://www.last.fm/tag/analphabete"},{"count":3,"name":"fautes de francais","url":"https://www.last.fm/tag/fautes+de+francais"},{"count":3,"name":"Need to Rate","url":"https://www.last.fm/tag/Need+to+Rate"},{"count":3,"name":"laglak","url":"https://www.last.fm/tag/laglak"},{"count":3,"name":"Wati daube","url":"https://www.last.fm/tag/Wati+daube"},{"count":3,"name":"folk depressif experimental a thematique introspective et psychanalytique","url":"https://www.last.fm/tag/folk+depressif+experimental+a+thematique+introspective+et+psychanalytique"},{"count":3,"name":"fitzboxtyp97","url":"https://www.last.fm/tag/fitzboxtyp97"},{"count":3,"name":"Lucenzo","url":"https://www.last.fm/tag/Lucenzo"},{"count":3,"name":"HUHUHUHU","url":"https://www.last.fm/tag/HUHUHUHU"},{"count":3,"name":"rap inconscient","url":"https://www.last.fm/tag/rap+inconscient"},{"count":3,"name":"unconscious rap","url":"https://www.last.fm/tag/unconscious+rap"},{"count":3,"name":"rai n b fever","url":"https://www.last.fm/tag/rai+n+b+fever"},{"count":3,"name":"WATI B","url":"https://www.last.fm/tag/WATI+B"},{"count":3,"name":"zeiinaab kiss","url":"https://www.last.fm/tag/zeiinaab+kiss"},{"count":3,"name":"ses trop bien","url":"https://www.last.fm/tag/ses+trop+bien"},{"count":3,"name":"watibigali","url":"https://www.last.fm/tag/watibigali"}],"@attr":{"artist":"Sexion d'Assaut"}}}