{"toptags":{"tag":[{"count":100,"name":"seen live","url":"https://www.last.fm/tag/seen+live"},{"count":97,"name":"indie","url":"https://www.last.fm/tag/indie"},{"count":75,"name":"Canadian","url":"https://www.last.fm/tag/Canadian"},{"count":71,"name":"indie rock","url":"https://www.last.fm/tag/indie+rock"},{"count":30,"name":"rock","url":"https://www.last.fm/tag/rock"},{"count":28,"name":"alternative","url":"https://www.last.fm/tag/alternative"},{"count":12,"name":"emo","url":"https://www.last.fm/tag/emo"},{"count":12,"name":"folk","url":"https://www.last.fm/tag/folk"},{"count":12,"name":"indie pop","url":"https://www.last.fm/tag/indie+pop"},{"count":11,"name":"punk","url":"https://www.last.fm/tag/punk"},{"count":7,"name":"canada","url":"https://www.last.fm/tag/canada"},{"count":7,"name":"Winnipeg","url":"https://www.last.fm/tag/Winnipeg"},{"count":5,"name":"folk rock","url":"https://www.last.fm/tag/folk+rock"},{"count":5,"name":"Alt-country","url":"https://www.last.fm/tag/Alt-country"},{"count":5,"name":"folk punk","url":"https://www.last.fm/tag/folk+punk"},{"count":4,"name":"alternative rock","url":"https://www.last.fm/tag/alternative+rock"},{"count":4,"name":"post-punk","url":"https://www.last.fm/tag/post-punk"},{"count":4,"name":"punk rock","url":"https://www.last.fm/tag/punk+rock"},{"count":3,"name":"pop","url":"https://www.last.fm/tag/pop"},{"count":3,"name":"singer-songwriter","url":"https://www.last.fm/tag/singer-songwriter"},{"count":3,"name":"canadian indie","url":"https://www.last.fm/tag/canadian+indie"},{"count":3,"name":"Great Lyricists","url":"https://www.last.fm/tag/Great+Lyricists"},{"count":2,"name":"favorites","url":"https://www.last.fm/tag/favorites"},{"count":2,"name":"pop punk","url":"https://www.last.fm/tag/pop+punk"},{"count":2,"name":"Love","url":"https://www.last.fm/tag/Love"},{"count":2,"name":"indie folk","url":"https://www.last.fm/tag/indie+folk"},{"count":2,"name":"manitoba","url":"https://www.last.fm/tag/manitoba"},{"count":2,"name":"acoustic","url":"https://www.last.fm/tag/acoustic"},{"count":2,"name":"Mellow","url":"https://www.last.fm/tag/Mellow"},{"count":2,"name":"amazing","url":"https://www.last.fm/tag/amazing"},{"count":2,"name":"literate","url":"https://www.last.fm/tag/literate"},{"count":2,"name":"male vocalists","url":"https://www.last.fm/tag/male+vocalists"},{"count":2,"name":"90s","url":"https://www.last.fm/tag/90s"},{"count":2,"name":"introspective","url":"https://www.last.fm/tag/introspective"},{"count":2,"name":"intelligent","url":"https://www.last.fm/tag/intelligent"},{"count":2,"name":"00s","url":"https://www.last.fm/tag/00s"},{"count":2,"name":"lyrical","url":"https://www.last.fm/tag/lyrical"},{"count":1,"name":"Awesome","url":"https://www.last.fm/tag/Awesome"},{"count":1,"name":"poetry","url":"https://www.last.fm/tag/poetry"},{"count":1,"name":"fun","url":"https://www.last.fm/tag/fun"},{"count":1,"name":"Pop-punk","url":"https://www.last.fm/tag/Pop-punk"},{"count":1,"name":"witty","url":"https://www.last.fm/tag/witty"},{"count":1,"name":"orgcore","url":"https://www.last.fm/tag/orgcore"},{"count":1,"name":"southside 2008","url":"https://www.last.fm/tag/southside+2008"},{"count":1,"name":"hurricane 08","url":"https://www.last.fm/tag/hurricane+08"}],"@attr":{"artist":"The Weakerthans"}}}