{"toptags":{"tag":[{"count":100,"name":"indie","url":"https://www.last.fm/tag/indie"},{"count":75,"name":"folk","url":"https://www.last.fm/tag/folk"},{"count":74,"name":"seen live","url":"https://www.last.fm/tag/seen+live"},{"count":70,"name":"british","url":"https://www.last.fm/tag/british"},{"count":66,"name":"singer-songwriter","url":"https://www.last.fm/tag/singer-songwriter"},{"count":48,"name":"piano","url":"https://www.last.fm/tag/piano"},{"count":13,"name":"male vocalist","url":"https://www.last.fm/tag/male+vocalist"},{"count":8,"name":"indie pop","url":"https://www.last.fm/tag/indie+pop"},{"count":6,"name":"indie folk","url":"https://www.last.fm/tag/indie+folk"},{"count":6,"name":"pop","url":"https://www.last.fm/tag/pop"},{"count":5,"name":"UK","url":"https://www.last.fm/tag/UK"},{"count":4,"name":"male vocalists","url":"https://www.last.fm/tag/male+vocalists"},{"count":3,"name":"alternative","url":"https://www.last.fm/tag/alternative"},{"count":3,"name":"piano rock","url":"https://www.last.fm/tag/piano+rock"},{"count":3,"name":"english","url":"https://www.last.fm/tag/english"},{"count":3,"name":"indie rock","url":"https://www.last.fm/tag/indie+rock"},{"count":3,"name":"acoustic","url":"https://www.last.fm/tag/acoustic"},{"count":2,"name":"electronic","url":"https://www.last.fm/tag/electronic"},{"count":2,"name":"soul","url":"https://www.last.fm/tag/soul"},{"count":2,"name":"cute","url":"https://www.last.fm/tag/cute"},{"count":2,"name":"singer songwriter","url":"https://www.last.fm/tag/singer+songwriter"},{"count":2,"name":"folk pop","url":"https://www.last.fm/tag/folk+pop"},{"count":2,"name":"love at first listen","url":"https://www.last.fm/tag/love+at+first+listen"},{"count":2,"name":"beautiful voice","url":"https://www.last.fm/tag/beautiful+voice"},{"count":2,"name":"All","url":"https://www.last.fm/tag/All"},{"count":2,"name":"bbc sound of 2013","url":"https://www.last.fm/tag/bbc+sound+of+2013"},{"count":2,"name":"Lowlands 2013","url":"https://www.last.fm/tag/Lowlands+2013"},{"count":2,"name":"tom odell","url":"https://www.last.fm/tag/tom+odell"}],"@attr":{"artist":"Tom Odell"}}}