{"toptags":{"tag":[{"count":100,"name":"chinese","url":"https://www.last.fm/tag/chinese"},{"count":82,"name":"pop","url":"https://www.last.fm/tag/pop"},{"count":69,"name":"singapore","url":"https://www.last.fm/tag/singapore"},{"count":46,"name":"C-pop","url":"https://www.last.fm/tag/C-pop"},{"count":40,"name":"mandarin","url":"https://www.last.fm/tag/mandarin"},{"count":31,"name":"female vocalists","url":"https://www.last.fm/tag/female+vocalists"},{"count":14,"name":"cpop","url":"https://www.last.fm/tag/cpop"},{"count":11,"name":"female","url":"https://www.last.fm/tag/female"},{"count":9,"name":"stefanie sun","url":"https://www.last.fm/tag/stefanie+sun"},{"count":7,"name":"Chinese Pop","url":"https://www.last.fm/tag/Chinese+Pop"},{"count":6,"name":"Asian","url":"https://www.last.fm/tag/Asian"},{"count":5,"name":"taiwan","url":"https://www.last.fm/tag/taiwan"},{"count":5,"name":"female vocalist","url":"https://www.last.fm/tag/female+vocalist"},{"count":5,"name":"Singaporean","url":"https://www.last.fm/tag/Singaporean"},{"count":4,"name":"yanzi","url":"https://www.last.fm/tag/yanzi"},{"count":3,"name":"mandopop","url":"https://www.last.fm/tag/mandopop"},{"count":3,"name":"Sun Yan Zi","url":"https://www.last.fm/tag/Sun+Yan+Zi"},{"count":3,"name":"sunyanzi","url":"https://www.last.fm/tag/sunyanzi"},{"count":3,"name":"Favorite","url":"https://www.last.fm/tag/Favorite"},{"count":3,"name":"Chinese Music","url":"https://www.last.fm/tag/Chinese+Music"},{"count":3,"name":"stefanie","url":"https://www.last.fm/tag/stefanie"},{"count":2,"name":"China","url":"https://www.last.fm/tag/China"},{"count":2,"name":"Asian Pop","url":"https://www.last.fm/tag/Asian+Pop"},{"count":2,"name":"japanese","url":"https://www.last.fm/tag/japanese"},{"count":2,"name":"Love","url":"https://www.last.fm/tag/Love"},{"count":2,"name":"female vocals","url":"https://www.last.fm/tag/female+vocals"},{"count":2,"name":"women","url":"https://www.last.fm/tag/women"},{"count":2,"name":"bigfatjiji","url":"https://www.last.fm/tag/bigfatjiji"},{"count":2,"name":"Stephanie Sun","url":"https://www.last.fm/tag/Stephanie+Sun"}],"@attr":{"artist":"孫燕姿"}}}